ezinterpret/__init__.py
ezinterpret/ezinterpret.py
ezinterpret-0.1.7.dist-info/AUTHORS.rst
ezinterpret-0.1.7.dist-info/LICENSE
ezinterpret-0.1.7.dist-info/METADATA
ezinterpret-0.1.7.dist-info/WHEEL
ezinterpret-0.1.7.dist-info/top_level.txt
ezinterpret-0.1.7.dist-info/RECORD
